zof/__init__.py
zof/__main__.py
zof/api_application.py
zof/api_args.py
zof/api_compile.py
zof/api_functions.py
zof/api_run.py
zof/asyncmap.py
zof/asyncmap36.py
zof/callbackinfo.py
zof/codec.py
zof/connection.py
zof/controller.py
zof/controllerapp.py
zof/datapath.py
zof/endpoint.py
zof/event.py
zof/exception.py
zof/handler.py
zof/http.py
zof/logging.py
zof/objectview.py
zof/ofctl.py
zof/pidfile.py
zof/pktview.py
zof/protocol.py
zof/run_server.py
zof/demo/__init__.py
zof/demo/autoresponder.py
zof/demo/bgp.py
zof/demo/cbenchreply.py
zof/demo/check.py
zof/demo/check_fields.py
zof/demo/command_shell.py
zof/demo/conntest.py
zof/demo/demo.py
zof/demo/hub.py
zof/demo/layer2.py
zof/demo/layer2mt.py
zof/demo/logger.py
zof/demo/metrics.py
zof/demo/oftr_bench.py
zof/demo/rest_api.py
zof/demo/simulator.py
zof/demo/table_features.py
zof/demo/zbench.py
zof/service/__init__.py
zof/service/datapath.py
zof-0.19.0.dist-info/DESCRIPTION.rst
zof-0.19.0.dist-info/METADATA
zof-0.19.0.dist-info/RECORD
zof-0.19.0.dist-info/WHEEL
zof-0.19.0.dist-info/metadata.json
zof-0.19.0.dist-info/top_level.txt
zof-0.19.0.dist-info/zip-safe
