Metadata-Version: 2.0
Name: zof
Version: 0.19.0
Summary: OpenFlow App Framework
Home-page: https://github.com/byllyfish/zof
Author: William W. Fisher
Author-email: william.w.fisher@gmail.com
License: MIT
Keywords: openflow controller
Platform: UNKNOWN
Classifier: Development Status :: 3 - Alpha
Classifier: Intended Audience :: Developers
Classifier: License :: OSI Approved :: MIT License
Classifier: Operating System :: Unix
Classifier: Programming Language :: Python :: 3.5
Classifier: Programming Language :: Python :: 3.6
Classifier: Topic :: System :: Networking
Requires-Dist: aiohttp
Requires-Dist: prometheus-client
